azimuth/__init__.py
azimuth/cli_predict.py
azimuth/cli_run_model.py
azimuth/cluster_job.py
azimuth/corrstats.py
azimuth/load_data.py
azimuth/local_multiprocessing.py
azimuth/metrics.py
azimuth/model_comparison.py
azimuth/predict.py
azimuth/util.py
azimuth/data/FC_plus_RES_withPredictions.csv
azimuth/data/V1_data.xlsx
azimuth/data/V1_suppl_data.txt
azimuth/data/V2_data.xlsx
azimuth/features/__init__.py
azimuth/features/featurization.py
azimuth/features/microhomology.py
azimuth/models/DNN.py
azimuth/models/GP.py
azimuth/models/__init__.py
azimuth/models/baselines.py
azimuth/models/ensembles.py
azimuth/models/gpy_ssk.py
azimuth/models/regression.py
azimuth/models/ssk.py
azimuth/saved_models/V3_model_full.pickle
azimuth/saved_models/V3_model_nopos.pickle
azimuth/tests/1000guides.csv
azimuth/tests/test_saved_models.py
Biomatters_Azimuth-0.2.6.dist-info/LICENSE.txt
Biomatters_Azimuth-0.2.6.dist-info/METADATA
Biomatters_Azimuth-0.2.6.dist-info/WHEEL
Biomatters_Azimuth-0.2.6.dist-info/top_level.txt
Biomatters_Azimuth-0.2.6.dist-info/RECORD
