Metadata-Version: 2.1
Name: Biomatters-Azimuth
Version: 0.2.6
Summary: Machine Learning-Based Predictive Modelling of CRISPR/Cas9 guide efficiency
Home-page: UNKNOWN
Author: Nicolo Fusi and Jennifer Listgarten
Author-email: fusi@microsoft.com, jennl@microsoft.com
License: BSD
Platform: UNKNOWN
License-File: LICENSE.txt
Requires-Dist: scipy
Requires-Dist: numpy (>=1.19.3)
Requires-Dist: nose
Requires-Dist: scikit-learn (==0.24.1)
Requires-Dist: pandas
Requires-Dist: biopython (<=1.79)
Requires-Dist: xlrd
